systemd_service_generator/__init__.py
systemd_service_generator/sdg.py
systemd_service_generator-1.0.2.dist-info/LICENSE
systemd_service_generator-1.0.2.dist-info/METADATA
systemd_service_generator-1.0.2.dist-info/WHEEL
systemd_service_generator-1.0.2.dist-info/entry_points.txt
systemd_service_generator-1.0.2.dist-info/top_level.txt
systemd_service_generator-1.0.2.dist-info/RECORD
