Metadata-Version: 2.1
Name: systemd_service_generator
Version: 1.0.2
Summary: A tool to generate systemd service files from a configuration file.
Home-page: https://github.com/kqiq/systemd_service_generator
Author: kqiq
Author-email: kqiqerl@gmail.com
Classifier: Programming Language :: Python :: 3
Classifier: License :: OSI Approved :: MIT License
Classifier: Operating System :: OS Independent
Requires-Python: >=3.6
License-File: LICENSE
